klazor_client/__init__.py
klazor_client/client.py
klazor_client/models.py
klazor_client/settings.py
klazor_client/test.py
klazor_client/utils.py
klazor_client-0.0.4.dist-info/LICENSE
klazor_client-0.0.4.dist-info/METADATA
klazor_client-0.0.4.dist-info/WHEEL
klazor_client-0.0.4.dist-info/top_level.txt
klazor_client-0.0.4.dist-info/RECORD
