Metadata-Version: 2.1
Name: klazor-client
Version: 0.0.4
Summary: A package that enables your app to communicate with klazor in a client-server way
Home-page: https://github.com/wilcoln/klazor-client
Author: Wilfried L. Bounsi
Author-email: wilcoln99@gmail.com
License: UNKNOWN
Platform: UNKNOWN
Classifier: Programming Language :: Python :: 3
Classifier: License :: OSI Approved :: MIT License
Classifier: Operating System :: OS Independent
Requires-Dist: requests
